log_datasets/__init__.py
log_datasets/dataset.py
log_datasets/datasets.py
utils/Drain.py
utils/__init__.py
utils/graphs_util.py
utils/window_utils.py
logs2graphs-1.1.14.dist-info/LICENCE
logs2graphs-1.1.14.dist-info/METADATA
logs2graphs-1.1.14.dist-info/WHEEL
logs2graphs-1.1.14.dist-info/top_level.txt
logs2graphs-1.1.14.dist-info/RECORD
