Metadata-Version: 2.1
Name: logs2graphs
Version: 1.1.14
Summary: Library for extraction of graph data from logs
Home-page: https://github.com/pypa/sampleproject
Author: Stefan Andonov
Author-email: stefan.andonov@finki.ukim.mk
Project-URL: Bug Tracker, https://github.com/pypa/sampleproject/issues
Classifier: Programming Language :: Python :: 3
Classifier: License :: OSI Approved :: MIT License
Classifier: Operating System :: OS Independent
Requires-Python: >=3.6
License-File: LICENCE
Requires-Dist: gdown
Requires-Dist: networkx
Requires-Dist: numpy
Requires-Dist: pandas
Requires-Dist: python-dateutil
Requires-Dist: regex
Requires-Dist: requests
Requires-Dist: pyvis
Requires-Dist: importlib-metadata ; python_version < "3.8"
